moonreader_tools/__init__.py
moonreader_tools/conf.py
moonreader_tools/datamodel/__init__.py
moonreader_tools/datamodel/annotation.py
moonreader_tools/datamodel/book.py
moonreader_tools/datamodel/statistics.py
moonreader_tools/errors.py
moonreader_tools/finders/__init__.py
moonreader_tools/finders/dropbox/__init__.py
moonreader_tools/finders/dropbox/finder.py
moonreader_tools/finders/dropbox/utils.py
moonreader_tools/finders/fs/__init__.py
moonreader_tools/finders/fs/finder.py
moonreader_tools/main.py
moonreader_tools/parsers/__init__.py
moonreader_tools/parsers/base.py
moonreader_tools/parsers/fb2_parser.py
moonreader_tools/parsers/file_reader.py
moonreader_tools/parsers/note_extractor.py
moonreader_tools/parsers/pdf_parser.py
moonreader_tools/parsers/stat_parser.py
moonreader_tools/utils.py
moonreader_tools-2.0.0.dist-info/entry_points.txt
moonreader_tools-2.0.0.dist-info/LICENSE.md
moonreader_tools-2.0.0.dist-info/WHEEL
moonreader_tools-2.0.0.dist-info/METADATA
moonreader_tools-2.0.0.dist-info/RECORD
