Metadata-Version: 2.1
Name: moonreader-tools
Version: 2.0.0
Summary: Library allowing to work with MoonReader book formats.
Home-page: https://github.com/MrLokans/MoonReader_tools
License: MIT
Author: MrLokans
Author-email: mrlokans@gmail.com
Requires-Python: >=3.8,<4.0
Classifier: License :: OSI Approved :: MIT License
Classifier: Programming Language :: Python :: 3
Classifier: Programming Language :: Python :: 3.10
Classifier: Programming Language :: Python :: 3.8
Classifier: Programming Language :: Python :: 3.9
Requires-Dist: dropbox (<12.0)
Project-URL: Repository, https://github.com/MrLokans/MoonReader_tools
